MANIFEST.in
README.rst
VERSION
setup.py
hitchbuildpy/__init__.py
hitchbuildpy/pyenv-commit-hash
hitchbuildpy/pyenv.py
hitchbuildpy/virtualenv.py
hitchbuildpy.egg-info/PKG-INFO
hitchbuildpy.egg-info/SOURCES.txt
hitchbuildpy.egg-info/dependency_links.txt
hitchbuildpy.egg-info/not-zip-safe
hitchbuildpy.egg-info/requires.txt
hitchbuildpy.egg-info/top_level.txt
hitchbuildpy/__pycache__/openssl.cpython-35.pyc
hitchbuildpy/__pycache__/openssl_build.cpython-35.pyc
hitchbuildpy/bin/python-build
hitchbuildpy/share/python-build/2.1.3
hitchbuildpy/share/python-build/2.2.3
hitchbuildpy/share/python-build/2.3.7
hitchbuildpy/share/python-build/2.4.0
hitchbuildpy/share/python-build/2.4.1
hitchbuildpy/share/python-build/2.4.2
hitchbuildpy/share/python-build/2.4.3
hitchbuildpy/share/python-build/2.4.4
hitchbuildpy/share/python-build/2.4.5
hitchbuildpy/share/python-build/2.4.6
hitchbuildpy/share/python-build/2.5.0
hitchbuildpy/share/python-build/2.5.1
hitchbuildpy/share/python-build/2.5.2
hitchbuildpy/share/python-build/2.5.3
hitchbuildpy/share/python-build/2.5.4
hitchbuildpy/share/python-build/2.5.5
hitchbuildpy/share/python-build/2.5.6
hitchbuildpy/share/python-build/2.6.6
hitchbuildpy/share/python-build/2.6.7
hitchbuildpy/share/python-build/2.6.8
hitchbuildpy/share/python-build/2.6.9
hitchbuildpy/share/python-build/2.7-dev
hitchbuildpy/share/python-build/2.7.0
hitchbuildpy/share/python-build/2.7.1
hitchbuildpy/share/python-build/2.7.10
hitchbuildpy/share/python-build/2.7.11
hitchbuildpy/share/python-build/2.7.12
hitchbuildpy/share/python-build/2.7.13
hitchbuildpy/share/python-build/2.7.14
hitchbuildpy/share/python-build/2.7.15
hitchbuildpy/share/python-build/2.7.16
hitchbuildpy/share/python-build/2.7.17
hitchbuildpy/share/python-build/2.7.18
hitchbuildpy/share/python-build/2.7.2
hitchbuildpy/share/python-build/2.7.3
hitchbuildpy/share/python-build/2.7.4
hitchbuildpy/share/python-build/2.7.5
hitchbuildpy/share/python-build/2.7.6
hitchbuildpy/share/python-build/2.7.7
hitchbuildpy/share/python-build/2.7.8
hitchbuildpy/share/python-build/2.7.9
hitchbuildpy/share/python-build/3.0.1
hitchbuildpy/share/python-build/3.1.0
hitchbuildpy/share/python-build/3.1.1
hitchbuildpy/share/python-build/3.1.2
